{
	"@type":"Process",
	"Name":"zBackup_Data_Archive",
	"HasSecurityAccess":false,
	"Code@Code.link":"zBackup_Data_Archive.ti",
	"UIData":"CubeAction=1511\fDataAction=1503\fCubeLogChanges=0\f",
	"DataSource":
	{
		"Type":"None"
	},
	"Parameters":
	[
		{
			"Name":"pNomArchive",
			"Prompt":"Quel nom voulez vous donner à l'archive ?",
			"Value":"exportDataTM1",
			"Type":"String"
		},
		{
			"Name":"pNbJours",
			"Prompt":"Combien de jours de backup voulez vous conserver ?",
			"Value":"200",
			"Type":"String"
		}
	],
	"Variables":[]
}