{
	"@type":"Subset",
	"Name":"2024_2025_Se29",
	"Elements":
	[
		{
			"@id":"Dimensions('Annee_Calendaire')/Hierarchies('Annee_Calendaire')/Elements('2024-10-20')"
		},
		{
			"@id":"Dimensions('Annee_Calendaire')/Hierarchies('Annee_Calendaire')/Elements('2024-10-19')"
		},
		{
			"@id":"Dimensions('Annee_Calendaire')/Hierarchies('Annee_Calendaire')/Elements('2024-10-18')"
		},
		{
			"@id":"Dimensions('Annee_Calendaire')/Hierarchies('Annee_Calendaire')/Elements('2024-10-17')"
		},
		{
			"@id":"Dimensions('Annee_Calendaire')/Hierarchies('Annee_Calendaire')/Elements('2024-10-16')"
		},
		{
			"@id":"Dimensions('Annee_Calendaire')/Hierarchies('Annee_Calendaire')/Elements('2024-10-15')"
		},
		{
			"@id":"Dimensions('Annee_Calendaire')/Hierarchies('Annee_Calendaire')/Elements('2024-10-14')"
		}
	]
}