{
	"@type":"Subset",
	"Name":"2026_2027_Se27",
	"Elements":
	[
		{
			"@id":"Dimensions('Annee_Calendaire')/Hierarchies('Annee_Calendaire')/Elements('2026-10-11')"
		},
		{
			"@id":"Dimensions('Annee_Calendaire')/Hierarchies('Annee_Calendaire')/Elements('2026-10-10')"
		},
		{
			"@id":"Dimensions('Annee_Calendaire')/Hierarchies('Annee_Calendaire')/Elements('2026-10-09')"
		},
		{
			"@id":"Dimensions('Annee_Calendaire')/Hierarchies('Annee_Calendaire')/Elements('2026-10-08')"
		},
		{
			"@id":"Dimensions('Annee_Calendaire')/Hierarchies('Annee_Calendaire')/Elements('2026-10-07')"
		},
		{
			"@id":"Dimensions('Annee_Calendaire')/Hierarchies('Annee_Calendaire')/Elements('2026-10-06')"
		},
		{
			"@id":"Dimensions('Annee_Calendaire')/Hierarchies('Annee_Calendaire')/Elements('2026-10-05')"
		}
	]
}