{
	"@type":"Subset",
	"Name":"2030_2031_Se16",
	"Elements":
	[
		{
			"@id":"Dimensions('Annee_Calendaire')/Hierarchies('Annee_Calendaire')/Elements('2030-07-21')"
		},
		{
			"@id":"Dimensions('Annee_Calendaire')/Hierarchies('Annee_Calendaire')/Elements('2030-07-20')"
		},
		{
			"@id":"Dimensions('Annee_Calendaire')/Hierarchies('Annee_Calendaire')/Elements('2030-07-19')"
		},
		{
			"@id":"Dimensions('Annee_Calendaire')/Hierarchies('Annee_Calendaire')/Elements('2030-07-18')"
		},
		{
			"@id":"Dimensions('Annee_Calendaire')/Hierarchies('Annee_Calendaire')/Elements('2030-07-17')"
		},
		{
			"@id":"Dimensions('Annee_Calendaire')/Hierarchies('Annee_Calendaire')/Elements('2030-07-16')"
		},
		{
			"@id":"Dimensions('Annee_Calendaire')/Hierarchies('Annee_Calendaire')/Elements('2030-07-15')"
		}
	]
}