{
	"@type":"Subset",
	"Name":"2037_2038_Se33",
	"Elements":
	[
		{
			"@id":"Dimensions('Annee_Calendaire')/Hierarchies('Annee_Calendaire')/Elements('2037-11-22')"
		},
		{
			"@id":"Dimensions('Annee_Calendaire')/Hierarchies('Annee_Calendaire')/Elements('2037-11-21')"
		},
		{
			"@id":"Dimensions('Annee_Calendaire')/Hierarchies('Annee_Calendaire')/Elements('2037-11-20')"
		},
		{
			"@id":"Dimensions('Annee_Calendaire')/Hierarchies('Annee_Calendaire')/Elements('2037-11-19')"
		},
		{
			"@id":"Dimensions('Annee_Calendaire')/Hierarchies('Annee_Calendaire')/Elements('2037-11-18')"
		},
		{
			"@id":"Dimensions('Annee_Calendaire')/Hierarchies('Annee_Calendaire')/Elements('2037-11-17')"
		},
		{
			"@id":"Dimensions('Annee_Calendaire')/Hierarchies('Annee_Calendaire')/Elements('2037-11-16')"
		}
	]
}