{
	"@type":"Subset",
	"Name":"2039_2040_Se39",
	"Elements":
	[
		{
			"@id":"Dimensions('Annee_Calendaire')/Hierarchies('Annee_Calendaire')/Elements('2039-12-31')"
		},
		{
			"@id":"Dimensions('Annee_Calendaire')/Hierarchies('Annee_Calendaire')/Elements('2039-12-30')"
		},
		{
			"@id":"Dimensions('Annee_Calendaire')/Hierarchies('Annee_Calendaire')/Elements('2039-12-29')"
		},
		{
			"@id":"Dimensions('Annee_Calendaire')/Hierarchies('Annee_Calendaire')/Elements('2039-12-28')"
		},
		{
			"@id":"Dimensions('Annee_Calendaire')/Hierarchies('Annee_Calendaire')/Elements('2039-12-27')"
		},
		{
			"@id":"Dimensions('Annee_Calendaire')/Hierarchies('Annee_Calendaire')/Elements('2039-12-26')"
		},
		{
			"@id":"Dimensions('Annee_Calendaire')/Hierarchies('Annee_Calendaire')/Elements('2039-01-02')"
		},
		{
			"@id":"Dimensions('Annee_Calendaire')/Hierarchies('Annee_Calendaire')/Elements('2039-01-01')"
		}
	]
}